books/__init__.py
books/admin.py
books/apps.py
books/forms.py
books/migrations/0001_initial.py
books/migrations/__init__.py
books/models.py
books/templates/author_books_edit.html
books/templates/author_create.html
books/templates/author_detail.html
books/templates/author_list.html
books/templates/base.html
books/templates/home.html
books/tests.py
books/urls.py
books/views.py
aflabs_test_app-0.1.1.dist-info/METADATA
aflabs_test_app-0.1.1.dist-info/WHEEL
aflabs_test_app-0.1.1.dist-info/RECORD
