Metadata-Version: 2.1
Name: aflabs-test-app
Version: 0.1.1
Summary: no description
Author: Ziga Avbreht
Author-email: ziga.avbreht@gmail.com
Requires-Python: >=3.11,<4.0
Classifier: Programming Language :: Python :: 3
Classifier: Programming Language :: Python :: 3.11
Requires-Dist: Django (>=4.2.2,<5.0.0)
